dictstack/__init__.py
dictstack-0.1.1.dist-info/LICENSE
dictstack-0.1.1.dist-info/WHEEL
dictstack-0.1.1.dist-info/METADATA
dictstack-0.1.1.dist-info/RECORD
