Metadata-Version: 2.1
Name: dictstack
Version: 0.1.1
Summary: A multi-level dictionary that can overlay values in layers.
Home-page: https://github.com/lee-b/dictstack
License: MIT
Author: Lee Braiden
Author-email: leebraid@gmail.com
Requires-Python: >2.7
Classifier: License :: OSI Approved :: MIT License
Classifier: Programming Language :: Python :: 2
Classifier: Programming Language :: Python :: 3
Classifier: Programming Language :: Python :: 3.4
Classifier: Programming Language :: Python :: 3.5
Classifier: Programming Language :: Python :: 3.6
Classifier: Programming Language :: Python :: 3.7
Project-URL: Repository, https://github.com/lee-b/dictstack
